easysparql/__init__.py
easysparql/cacher.py
easysparql/easysparql.py
easysparql/easysparqlclass.py
tests/__init__.py
tests/test_cache.py
tests/test_class.py
tests/test_functions.py
easysparql-1.6.2.dist-info/LICENSE
easysparql-1.6.2.dist-info/METADATA
easysparql-1.6.2.dist-info/WHEEL
easysparql-1.6.2.dist-info/top_level.txt
easysparql-1.6.2.dist-info/RECORD
