Metadata-Version: 2.1
Name: easysparql
Version: 1.6.2
Summary: A python wrapper to easily query knowledge graphs with SPARQL
Home-page: https://github.com/oeg-upm/easysparql
Author: Ahmad Alobaid
Author-email: aalobaid@fi.upm.es
License: UNKNOWN
Platform: UNKNOWN
Classifier: Programming Language :: Python :: 3
Classifier: License :: OSI Approved :: Apache Software License
Classifier: Operating System :: OS Independent
Requires-Python: >=3.6
Requires-Dist: SPARQLWrapper
